wtx_fs_mcp/__init__.py
wtx_fs_mcp-0.1.0.dist-info/WHEEL
wtx_fs_mcp-0.1.0.dist-info/entry_points.txt
wtx_fs_mcp-0.1.0.dist-info/METADATA
wtx_fs_mcp-0.1.0.dist-info/RECORD
