Metadata-Version: 2.3
Name: wtx-fs-mcp
Version: 0.1.0
Summary: 本地文件的各类操作: 移动、复制等。支持文件和文件夹
Author: lishuai
Author-email: lishuai <lis@geovis.com.cn>
Requires-Dist: mcp[cli]>=1.25.0
Requires-Python: >=3.10
